spdx_license_list/__init__.py
spdx_license_list/py.typed
spdx_license_list-3.27.0.dist-info/LICENSE
spdx_license_list-3.27.0.dist-info/METADATA
spdx_license_list-3.27.0.dist-info/WHEEL
spdx_license_list-3.27.0.dist-info/RECORD
