Metadata-Version: 2.3
Name: spdx-license-list
Version: 3.27.0
Summary: SPDX License List as a Python dictionary
License: MIT
Author: JJMC89
Requires-Python: >=3.9
Classifier: License :: OSI Approved :: MIT License
Classifier: Natural Language :: English
Classifier: Operating System :: OS Independent
Classifier: Programming Language :: Python :: 3 :: Only
Classifier: Typing :: Typed
Project-URL: source, https://github.com/JJMC89/spdx-license-list
